h1stars_payment_sdk-1.0.0.dist-info/licenses/LICENSE
h1stars_sdk/__init__.py
h1stars_sdk/client.py
h1stars_sdk/exceptions.py
h1stars_payment_sdk-1.0.0.dist-info/METADATA
h1stars_payment_sdk-1.0.0.dist-info/WHEEL
h1stars_payment_sdk-1.0.0.dist-info/top_level.txt
h1stars_payment_sdk-1.0.0.dist-info/RECORD
