Metadata-Version: 2.4
Name: h1stars-payment-sdk
Version: 1.0.0
Summary: Python SDK for H1Stars Payment Gateway
Home-page: https://github.com/h1gurodev/h1stars-python-sdk
Author: h1stars
Author-email: predmetdev@gmail.com
Project-URL: Bug Reports, https://github.com/h1gurodev/h1stars-python-sdk/issues
Project-URL: Source, https://github.com/h1gurodev/h1stars-python-sdk
Project-URL: Documentation, https://pay.h1stars.ru/docs
Keywords: payment gateway h1stars api sdk
Classifier: Development Status :: 5 - Production/Stable
Classifier: Intended Audience :: Developers
Classifier: Topic :: Software Development :: Libraries :: Python Modules
Classifier: License :: OSI Approved :: MIT License
Classifier: Programming Language :: Python :: 3
Classifier: Programming Language :: Python :: 3.6
Classifier: Programming Language :: Python :: 3.7
Classifier: Programming Language :: Python :: 3.8
Classifier: Programming Language :: Python :: 3.9
Classifier: Programming Language :: Python :: 3.10
Classifier: Programming Language :: Python :: 3.11
Requires-Python: >=3.6
License-File: LICENSE
Requires-Dist: aiohttp>=3.8.0
Provides-Extra: examples
Requires-Dist: fastapi>=0.95.0; extra == "examples"
Requires-Dist: uvicorn>=0.20.0; extra == "examples"
Dynamic: author
Dynamic: author-email
Dynamic: classifier
Dynamic: description
Dynamic: description-content-type
Dynamic: home-page
Dynamic: keywords
Dynamic: license-file
Dynamic: project-url
Dynamic: provides-extra
Dynamic: requires-dist
Dynamic: requires-python
Dynamic: summary
